{"name":"build-javascript","namedChunkGroups":{"polyfill":{"name":"polyfill","assets":[{"name":"webpack-runtime-9ec863635bc8bec23945.js","size":4055},{"name":"polyfill-f00c4ba88e6bd7f4c4ef.js","size":85854}],"filteredAssets":0,"assetsSize":89909,"filteredAuxiliaryAssets":2,"auxiliaryAssetsSize":223957},"app":{"name":"app","assets":[{"name":"webpack-runtime-9ec863635bc8bec23945.js","size":4055},{"name":"framework-1e399c4a989d4a2ccf62.js","size":130486},{"name":"styles.31d6cfe0d16ae931b73c.css","size":0},{"name":"app-0b2a9e771afcb002bae1.js","size":333801}],"filteredAssets":0,"assetsSize":468342,"filteredAuxiliaryAssets":3,"auxiliaryAssetsSize":1711984},"component---src-pages-booking-app-booking-aspx-tsx":{"name":"component---src-pages-booking-app-booking-aspx-tsx","assets":[{"name":"framework-1e399c4a989d4a2ccf62.js","size":130486},{"name":"commons-9528bfac068a1eb42fe8.js","size":27585},{"name":"component---src-pages-booking-app-booking-aspx-tsx-0c4c1a57f1af81e3017f.js","size":18251}],"filteredAssets":0,"assetsSize":176322,"filteredAuxiliaryAssets":3,"auxiliaryAssetsSize":499660},"component---src-pages-booking-app-result-aspx-tsx":{"name":"component---src-pages-booking-app-result-aspx-tsx","assets":[{"name":"framework-1e399c4a989d4a2ccf62.js","size":130486},{"name":"commons-9528bfac068a1eb42fe8.js","size":27585},{"name":"component---src-pages-booking-app-result-aspx-tsx-ac59b5889dd8448dea9d.js","size":674}],"filteredAssets":0,"assetsSize":158745,"filteredAuxiliaryAssets":3,"auxiliaryAssetsSize":434728},"component---src-pages-index-tsx":{"name":"component---src-pages-index-tsx","assets":[{"name":"framework-1e399c4a989d4a2ccf62.js","size":130486},{"name":"commons-9528bfac068a1eb42fe8.js","size":27585},{"name":"component---src-pages-index-tsx-5200f5e22c79a3fcb280.js","size":3545}],"filteredAssets":0,"assetsSize":161616,"filteredAuxiliaryAssets":4,"auxiliaryAssetsSize":1374971}},"assetsByChunkName":{"polyfill":["webpack-runtime-9ec863635bc8bec23945.js","polyfill-f00c4ba88e6bd7f4c4ef.js"],"app":["webpack-runtime-9ec863635bc8bec23945.js","framework-1e399c4a989d4a2ccf62.js","styles.31d6cfe0d16ae931b73c.css","app-0b2a9e771afcb002bae1.js"],"component---src-pages-booking-app-booking-aspx-tsx":["framework-1e399c4a989d4a2ccf62.js","commons-9528bfac068a1eb42fe8.js","component---src-pages-booking-app-booking-aspx-tsx-0c4c1a57f1af81e3017f.js"],"component---src-pages-booking-app-result-aspx-tsx":["framework-1e399c4a989d4a2ccf62.js","commons-9528bfac068a1eb42fe8.js","component---src-pages-booking-app-result-aspx-tsx-ac59b5889dd8448dea9d.js"],"component---src-pages-index-tsx":["framework-1e399c4a989d4a2ccf62.js","commons-9528bfac068a1eb42fe8.js","component---src-pages-index-tsx-5200f5e22c79a3fcb280.js"]},"childAssetsByChunkName":{}}